.flake8
.gitignore
.isort.cfg
.pre-commit-config.yaml
.pre-commit-hooks.yaml
.taskcluster.yml
MANIFEST.in
README.md
VERSION
requirements.txt
setup.py
test-requirements.txt
.github/dependabot.yml
taskcluster_yml_validator/__init__.py
taskcluster_yml_validator.egg-info/PKG-INFO
taskcluster_yml_validator.egg-info/SOURCES.txt
taskcluster_yml_validator.egg-info/dependency_links.txt
taskcluster_yml_validator.egg-info/entry_points.txt
taskcluster_yml_validator.egg-info/requires.txt
taskcluster_yml_validator.egg-info/top_level.txt
taskcluster_yml_validator/events/__init__.py
taskcluster_yml_validator/events/pull_request_open.py
taskcluster_yml_validator/events/push.py
taskcluster_yml_validator/events/tag_push.py